django_querysets_single_query_fetch/__init__.py
django_querysets_single_query_fetch/apps.py
django_querysets_single_query_fetch/service.py
django_querysets_single_query_fetch/migrations/__init__.py
django_querysets_single_query_fetch-0.0.13.dist-info/METADATA
django_querysets_single_query_fetch-0.0.13.dist-info/WHEEL
django_querysets_single_query_fetch-0.0.13.dist-info/top_level.txt
django_querysets_single_query_fetch-0.0.13.dist-info/RECORD
