Metadata-Version: 2.4
Name: django-querysets-single-query-fetch
Version: 0.0.13
Summary: Execute multiple Django querysets in a single SQL query
Author-email: Nishant Singh <nishant.singh@mydukaan.io>
License-Expression: Apache-2.0
Project-URL: Homepage, https://github.com/iNishant/django-querysets-single-query-fetch
Project-URL: Repository, https://github.com/iNishant/django-querysets-single-query-fetch
Classifier: Development Status :: 4 - Beta
Classifier: Framework :: Django
Classifier: Framework :: Django :: 4.0
Classifier: Framework :: Django :: 4.1
Classifier: Framework :: Django :: 4.2
Classifier: Framework :: Django :: 5.0
Classifier: Framework :: Django :: 5.1
Classifier: Intended Audience :: Developers
Classifier: Operating System :: OS Independent
Classifier: Programming Language :: Python :: 3
Classifier: Programming Language :: Python :: 3.9
Classifier: Programming Language :: Python :: 3.10
Classifier: Programming Language :: Python :: 3.11
Classifier: Topic :: Database
Classifier: Topic :: Software Development :: Libraries :: Python Modules
Requires-Python: >=3.9
Requires-Dist: django<5.3,>=4.0
Provides-Extra: dev
Requires-Dist: ruff==0.3.7; extra == "dev"
Requires-Dist: model-bakery==1.17.0; extra == "dev"
Requires-Dist: build==1.2.1; extra == "dev"
Requires-Dist: twine==5.0.0; extra == "dev"
Requires-Dist: mypy==1.10.0; extra == "dev"
Requires-Dist: mypy-extensions==1.0.0; extra == "dev"
